layx/__init__.py
layx/py.typed
layx-0.1.0.dist-info/METADATA
layx-0.1.0.dist-info/WHEEL
layx-0.1.0.dist-info/RECORD
